Metadata-Version: 2.3
Name: yta-ai-gemini
Version: 0.0.1
Summary: Youtube Autonomous AI Gemini Module.
Author: danialcala94
Author-email: danielalcalavalera@gmail.com
Requires-Python: ==3.9
Classifier: Programming Language :: Python :: 3
Classifier: Programming Language :: Python :: 3.9
Requires-Dist: google-generativeai (>=0.6.0,<2.0.0)
Requires-Dist: yta_programming (>=0.0.1,<1.0.0)
Requires-Dist: yta_validation (>=0.0.1,<1.0.0)
